template/__init__.py
template/models.py
template/template.py
utest/__init__.py
pycybos-0.0.0.dist-info/LICENSE
pycybos-0.0.0.dist-info/METADATA
pycybos-0.0.0.dist-info/WHEEL
pycybos-0.0.0.dist-info/top_level.txt
pycybos-0.0.0.dist-info/RECORD
