Metadata-Version: 2.1
Name: pycybos
Version: 0.0.0
Summary: Wrapper for 대신증권 CYBOS Plus Open API
Home-page: https://github.com/innovata/pycybos
Author: innovata sambong
Author-email: iinnovata@gmail.com
License: UNKNOWN
Platform: UNKNOWN
Classifier: Programming Language :: Python :: 3
Classifier: License :: OSI Approved :: MIT License
Classifier: Operating System :: OS Independent
Requires-Python: >=3.7
